isoark/__init__.py
isoark-0.0.0.dev0.dist-info/licenses/LICENSE
isoark-0.0.0.dev0.dist-info/METADATA
isoark-0.0.0.dev0.dist-info/WHEEL
isoark-0.0.0.dev0.dist-info/top_level.txt
isoark-0.0.0.dev0.dist-info/RECORD
