Metadata-Version: 2.4
Name: isoark
Version: 0.0.0.dev0
Summary: A Python package for templating projects.
Author-email: "mesotron.dev" <mail@mesotron.dev>
Maintainer-email: "mesotron.dev" <mail@mesotron.dev>
License:                                  Apache License
Project-URL: Homepage, https://github.com/nortosem/isoark
Project-URL: Documentation, https://github.com/nortosem/isoark/blob/trunk/README.md
Keywords: Python,template,skeleton,scaffolding,Jinja2,package,packaging,project,project templates
Classifier: Development Status :: 1 - Planning
Classifier: Intended Audience :: Developers
Classifier: License :: OSI Approved :: Apache Software License
Classifier: Operating System :: OS Independent
Classifier: Programming Language :: Python :: 3
Classifier: Programming Language :: Python :: 3.12
Classifier: Programming Language :: Python :: 3.13
Classifier: Topic :: Software Development :: Build Tools
Classifier: Topic :: Software Development :: Libraries :: Python Modules
Classifier: Typing :: Typed
Classifier: Topic :: Utilities
Requires-Python: >=3.12
License-File: LICENSE
Dynamic: license-file
